[{"C:\\Users\\Administrator\\Desktop\\omsp_timerA.v": "ASCII"}, {"E:\\work\\mod_sim\\io_cell.v": "ASCII"}, {"F:\\mydata\\Sublime Text Build 3083 x64\\Data\\Packages\\User\\Base File.sublime-settings": "ASCII"}, {"F:\\mydata\\Sublime Text Build 3083 x64\\Data\\Packages\\User\\Default (Windows).sublime-keymap": "ASCII"}, {"C:\\Users\\Administrator\\Desktop\\dma_decode_16b.v": "ASCII"}, {"F:\\mydata\\Sublime Text Build 3083 x64\\Data\\Packages\\User\\always.sublime-snippet": "ASCII"}, {"F:\\mydata\\Sublime Text Build 3083 x64\\Data\\Packages\\FileHeader\\FileHeader.sublime-settings": "ASCII"}, {"F:\\mydata\\Sublime Text Build 3083 x64\\Data\\Packages\\User\\FileHeader.sublime-settings": "ASCII"}, {"F:\\mydata\\Sublime Text Build 3083 x64\\Data\\Packages\\FileHeader\\Default (Windows).sublime-keymap": "ASCII"}, {"E:\\work\\mod_sim\\omsp_gpio.v": "ASCII"}, {"E:\\Program Files\\Sublime Text Build 3083 x64\\Data\\Packages\\User\\Default (Windows).sublime-keymap": "ASCII"}, {"C:\\cygwin64\\home\\cxhy\\pmem2ihex_shell": "ASCII"}, {"C:\\Users\\cxhy\\Desktop\\msp430sim": "ASCII"}, {"E:\\work\\mod_sim\\tb_openMSP430.do": "UTF-8"}, {"E:\\work\\mod_sim\\dma_channel.vhd": "UTF-8"}, {"E:\\work\\mod_sim\\dma_master.v": "GB2312"}, {"E:\\download\\xunlei\\Sublime Text Build 3083 x64\\Data\\Packages\\User\\Default (Windows).sublime-keymap": "ASCII"}, {"E:\\work\\mod_sim\\omsp_clock_module.v": "ASCII"}]